<annotation>
  <folder>1</folder>
  <filename>953/2.png</filename>
  <source>
    <database>CKdemo</database>
    <annotation>VOC</annotation>
    <image>CK</image>
  </source>
  <size>
    <width>640</width>
    <height>480</height>
    <depth>3</depth>
  </size>
  <segmented>0</segmented>
  <object>
    <name>shine</name>
    <pose/>
    <truncated>0</truncated>
    <difficult>0</difficult>
    <bndbox>
      <xmin>231</xmin>
      <ymin>312</ymin>
      <xmax>237</xmax>
      <ymax>318</ymax>
    </bndbox>
  </object>
  <object>
    <name>shine</name>
    <pose/>
    <truncated>0</truncated>
    <difficult>0</difficult>
    <bndbox>
      <xmin>357</xmin>
      <ymin>414</ymin>
      <xmax>363</xmax>
      <ymax>420</ymax>
    </bndbox>
  </object>
  <object>
    <name>shine</name>
    <pose/>
    <truncated>0</truncated>
    <difficult>0</difficult>
    <bndbox>
      <xmin>395</xmin>
      <ymin>437</ymin>
      <xmax>401</xmax>
      <ymax>443</ymax>
    </bndbox>
  </object>
  <object>
    <name>shine</name>
    <pose/>
    <truncated>0</truncated>
    <difficult>0</difficult>
    <bndbox>
      <xmin>361</xmin>
      <ymin>137</ymin>
      <xmax>367</xmax>
      <ymax>143</ymax>
    </bndbox>
  </object>
</annotation>
